qr_code/__init__.py
qr_code/apps.py
qr_code/urls.py
qr_code/views.py
qr_code/qrcode/__init__.py
qr_code/qrcode/constants.py
qr_code/qrcode/maker.py
qr_code/qrcode/serve.py
qr_code/qrcode/utils.py
qr_code/templatetags/__init__.py
qr_code/templatetags/qr_code.py
django_qr_code-4.1.0.dist-info/LICENSE
django_qr_code-4.1.0.dist-info/METADATA
django_qr_code-4.1.0.dist-info/WHEEL
django_qr_code-4.1.0.dist-info/top_level.txt
django_qr_code-4.1.0.dist-info/RECORD
