Metadata-Version: 2.1
Name: django-qr-code
Version: 4.1.0
Summary: An application that provides tools for displaying QR codes on your Django site.
Home-page: https://github.com/dprog-philippe-docourt/django-qr-code
Author: Philippe Docourt
Author-email: philippe@docourt.ch
Maintainer: Philippe Docourt
License: BSD 3-clause
Keywords: qr code django
Classifier: Development Status :: 5 - Production/Stable
Classifier: Intended Audience :: Developers
Classifier: Topic :: Software Development :: Libraries :: Python Modules
Classifier: Topic :: Internet :: WWW/HTTP
Classifier: License :: OSI Approved :: BSD License
Classifier: Programming Language :: Python :: 3 :: Only
Classifier: Framework :: Django :: 4.2
Classifier: Framework :: Django :: 5.0
Classifier: Natural Language :: English
Requires-Python: >=3.10
License-File: LICENSE
Requires-Dist: segno>=1.6
Requires-Dist: django>=4.2
Requires-Dist: pydantic>=2.7
